{
  "rp_customer": "Mamta Hardware",
  "receive_payment_date": "May 2025, May 14, 2025",
  "rp_payment_method": "cash",
  "rp_deposit_to": "NJ Bank",
  "invoices_to_check": [
    {
      "invoice_no": "Invoice #INV-00026",
      "payment_amount": "20"
    },
    {
      "invoice_no": "Invoice #INV-00025",
      "payment_amount": "20"
    }


  ],
  "credits_to_check":[
    {
      "credits_no": "#CR-00010",
      "credits_payment_amount": "10"
    },
    {
      "credits_no": "#CR-00005",
      "credits_payment_amount": "10"
    }

  ],
  "rp_memo": "test payment"
}